explaintheDQ/__init__.py
explaintheDQ/cli.py
explaintheDQ/explaintheDQ.py
explaintheDQ/jwst_dq_table.csv
explaintheDQ-0.1.2.dist-info/LICENSE
explaintheDQ-0.1.2.dist-info/METADATA
explaintheDQ-0.1.2.dist-info/WHEEL
explaintheDQ-0.1.2.dist-info/entry_points.txt
explaintheDQ-0.1.2.dist-info/top_level.txt
explaintheDQ-0.1.2.dist-info/RECORD
