Metadata-Version: 2.1
Name: explaintheDQ
Version: 0.1.2
Summary: explains the JWST DQ value
Home-page: https://github.com/eas342/explaintheDQ
Author: Everett Schlawin
Author-email: granfalloontoyballoon@hotmail.com
License: MIT license
Keywords: explaintheDQ
Classifier: Development Status :: 2 - Pre-Alpha
Classifier: Intended Audience :: Developers
Classifier: License :: OSI Approved :: MIT License
Classifier: Natural Language :: English
Classifier: Programming Language :: Python :: 3
Classifier: Programming Language :: Python :: 3.6
Classifier: Programming Language :: Python :: 3.7
Classifier: Programming Language :: Python :: 3.8
Requires-Python: >=3.6
License-File: LICENSE
Requires-Dist: astropy
